mini_orange_lib/__init__.py
mini_orange_lib/config.py
mini_orange_lib/exceptions.py
mini_orange_lib/jwt_manager.py
mini_orange_lib/mini_orange_library.py
mini_orange_lib/token_service.py
mini_orange_lib/flows/__init__.py
mini_orange_lib/flows/authorization_code_flow.py
mini_orange_lib/flows/base_flow.py
mini_orange_lib/flows/implicit_authorization_flow.py
mini_orange_lib/flows/password_grant_flow.py
mini_orange_lib/flows/pkce_authorization_flow.py
mini_orange_lib/utils/__init__.py
mini_orange_lib/utils/pkce_utils.py
mini_orange_lib/utils/public_key_utils.py
miniOrange-1.2.7.dist-info/LICENSE
miniOrange-1.2.7.dist-info/METADATA
miniOrange-1.2.7.dist-info/WHEEL
miniOrange-1.2.7.dist-info/top_level.txt
miniOrange-1.2.7.dist-info/RECORD
