Metadata-Version: 2.1
Name: miniOrange
Version: 1.2.7
Summary: OAuth Implementation With SSo
Author: Ayushi Agrawal
Author-email: ashayuparth@gmail.com
Classifier: Programming Language :: Python :: 3
Classifier: Operating System :: Unix
Classifier: Operating System :: MacOS :: MacOS X
Classifier: Operating System :: Microsoft :: Windows
License-File: LICENSE
